printDelay/__init__.py
printDelay/printDelay.py
printDelay-0.1.1.dist-info/LICENSE
printDelay-0.1.1.dist-info/METADATA
printDelay-0.1.1.dist-info/WHEEL
printDelay-0.1.1.dist-info/top_level.txt
printDelay-0.1.1.dist-info/RECORD
